[{"nombres":"Galván S.L.","direccion":"8260 Sara Quinta","ruc":"3401822014","empresasId":1},{"nombres":"Sanches, Gallegos and Robles","direccion":"60223 Beatriz Colegio","ruc":"8046678813","empresasId":1},{"nombres":"Vera Hermanos","direccion":"96152 Cristina Huerta","ruc":"0605593764","empresasId":1},{"nombres":"Campos - Polanco","direccion":"16795 Pedroza Aldea","ruc":"0932585590","empresasId":2},{"nombres":"Rodríguez - Patiño","direccion":"16543 Gustavo Parque","ruc":"1001176837","empresasId":2},{"nombres":"Sevilla S.L.","direccion":"61344 Conchita Puente","ruc":"8739092805","empresasId":2},{"nombres":"Gollum Hermanos","direccion":"2417 Colón Salida","ruc":"7035056547","empresasId":3},{"nombres":"Hernandes, Tello and Magaña","direccion":"25544 Cornejo Explanada","ruc":"7058348849","empresasId":3},{"nombres":"Colón e Hijos","direccion":"926 Osorio Parque","ruc":"7876551921","empresasId":3},{"nombres":"Molina, Cavazos and Portillo","direccion":"3852 Jaimes Puerta","ruc":"8507270886","empresasId":4},{"nombres":"Rendón - Pulido","direccion":"3261 Gerardo Riera","ruc":"3322029724","empresasId":4},{"nombres":"Pichardo, Arriaga and Dueñas","direccion":"071 Huerta Calle","ruc":"6509701883","empresasId":4},{"nombres":"Linares S.A.","direccion":"033 Pedro Rambla","ruc":"1365440497","empresasId":5},{"nombres":"Tello e Hijos","direccion":"46528 Ávalos Arroyo","ruc":"8861503326","empresasId":5},{"nombres":"Cazares, Becerra and Brito","direccion":"9080 Federico Travesía","ruc":"2885904092","empresasId":5}]
